README.md
setup.py
lbrlabs_scaleway/__init__.py
lbrlabs_scaleway/_inputs.py
lbrlabs_scaleway/_utilities.py
lbrlabs_scaleway/account_ssh_key.py
lbrlabs_scaleway/apple_slicon_valley_server.py
lbrlabs_scaleway/baremetal_server.py
lbrlabs_scaleway/container.py
lbrlabs_scaleway/container_cron.py
lbrlabs_scaleway/container_namespace.py
lbrlabs_scaleway/database.py
lbrlabs_scaleway/database_acl.py
lbrlabs_scaleway/database_backup.py
lbrlabs_scaleway/database_instance.py
lbrlabs_scaleway/database_privilege.py
lbrlabs_scaleway/database_read_replica.py
lbrlabs_scaleway/database_user.py
lbrlabs_scaleway/domain_record.py
lbrlabs_scaleway/domain_zone.py
lbrlabs_scaleway/flexible_ip.py
lbrlabs_scaleway/function.py
lbrlabs_scaleway/function_cron.py
lbrlabs_scaleway/function_namespace.py
lbrlabs_scaleway/get_account_ssh_key.py
lbrlabs_scaleway/get_baremetal_offer.py
lbrlabs_scaleway/get_baremetal_os.py
lbrlabs_scaleway/get_baremetal_server.py
lbrlabs_scaleway/get_container.py
lbrlabs_scaleway/get_container_namespace.py
lbrlabs_scaleway/get_database.py
lbrlabs_scaleway/get_database_acl.py
lbrlabs_scaleway/get_database_backup.py
lbrlabs_scaleway/get_database_instance.py
lbrlabs_scaleway/get_database_privilege.py
lbrlabs_scaleway/get_domain_record.py
lbrlabs_scaleway/get_domain_zone.py
lbrlabs_scaleway/get_flexible_ip.py
lbrlabs_scaleway/get_function.py
lbrlabs_scaleway/get_function_namespace.py
lbrlabs_scaleway/get_instance_image.py
lbrlabs_scaleway/get_instance_ip.py
lbrlabs_scaleway/get_instance_security_group.py
lbrlabs_scaleway/get_instance_server.py
lbrlabs_scaleway/get_instance_servers.py
lbrlabs_scaleway/get_instance_volume.py
lbrlabs_scaleway/get_iot_device.py
lbrlabs_scaleway/get_iot_hub.py
lbrlabs_scaleway/get_kubernetes_cluster.py
lbrlabs_scaleway/get_kubernetes_node_pool.py
lbrlabs_scaleway/get_loadbalancer.py
lbrlabs_scaleway/get_loadbalancer_certificate.py
lbrlabs_scaleway/get_loadbalancer_ip.py
lbrlabs_scaleway/get_marketplace_image.py
lbrlabs_scaleway.egg-info/PKG-INFO
lbrlabs_scaleway.egg-info/SOURCES.txt
lbrlabs_scaleway.egg-info/dependency_links.txt
lbrlabs_scaleway.egg-info/not-zip-safe
lbrlabs_scaleway.egg-info/requires.txt
lbrlabs_scaleway.egg-info/top_level.txt
