Metadata-Version: 2.1
Name: lbrlabs-scaleway
Version: 0.4.1a1662912002
Summary: A Pulumi package for creating and managing scaleway cloud resources.
Home-page: https://leebriggs.co.uk/projects#pulumi-scaleway
License: Apache-2.0
Project-URL: Repository, https://github.com/lbrlabs/pulumi-scaleway
Keywords: pulumi scaleway lbrlabs
Platform: UNKNOWN
